notifyr/__init__.py
notifyr/agents.py
notifyr/functions.py
notifyr-1.1.dist-info/LICENSE
notifyr-1.1.dist-info/METADATA
notifyr-1.1.dist-info/WHEEL
notifyr-1.1.dist-info/top_level.txt
notifyr-1.1.dist-info/RECORD
