Metadata-Version: 2.1
Name: notifyr
Version: 1.1
Summary: Object notification tool that implements observer design pattern at runtime
Home-page: https://github.com/victorcmoura/notifyr
Author: Victor Moura
Author-email: victor_cmoura@hotmail.com
License: GPL-3.0
Platform: UNKNOWN
